loaders/__init__.py
loaders/common/__init__.py
loaders/common/base_loader.py
loaders/google_drive_loader/__init__.py
loaders/google_drive_loader/common/__init__.py
loaders/google_drive_loader/common/base_loader.py
loaders/google_drive_loader/common/config.py
loaders/google_drive_loader/common/tests/__init__.py
loaders/google_drive_loader/docs_and_sheets_loader/__init__.py
loaders/google_drive_loader/docs_and_sheets_loader/docs_and_sheets_loader.py
loaders/google_drive_loader/docs_and_sheets_loader/tests/__init__.py
loaders/google_drive_loader/pdf_loader/__init__.py
loaders/google_drive_loader/pdf_loader/pdf_loader.py
loaders/google_drive_loader/pdf_loader/tests/__init__.py
loaders/notion_loader/__init__.py
loaders/notion_loader/config.py
loaders/notion_loader/notion_loader.py
loaders/notion_loader/notion/__init__.py
loaders/notion_loader/notion/api_wrapper.py
loaders/notion_loader/notion/blocks.py
loaders/notion_loader/notion/client.py
loaders/notion_loader/notion/database.py
loaders/notion_loader/notion/page.py
loaders/notion_loader/tests/__init__.py
loaders/notion_loader/tests/constants.py
loaders/notion_loader/tests/mocks.py
loaders/notion_loader/tests/test_block.py
loaders/notion_loader/tests/test_database.py
loaders/notion_loader/tests/test_page.py
loaders/sql_query_loader/__init__.py
loaders/sql_query_loader/sql_query_loader.py
loaders/web_loader/__init__.py
loaders/web_loader/config.py
loaders/web_loader/web_loader.py
loaders/web_loader/tests/__init__.py
logger/__init__.py
logger/logger.py
rs_docs_loader-0.1.1.dist-info/METADATA
rs_docs_loader-0.1.1.dist-info/WHEEL
rs_docs_loader-0.1.1.dist-info/top_level.txt
rs_docs_loader-0.1.1.dist-info/RECORD
